ocrbridge/__init__.py
ocrbridge/engines/__init__.py
ocrbridge/engines/easyocr/__init__.py
ocrbridge/engines/easyocr/engine.py
ocrbridge/engines/easyocr/hocr.py
ocrbridge/engines/easyocr/models.py
ocrbridge_easyocr-3.1.1.dist-info/METADATA
ocrbridge_easyocr-3.1.1.dist-info/WHEEL
ocrbridge_easyocr-3.1.1.dist-info/entry_points.txt
ocrbridge_easyocr-3.1.1.dist-info/licenses/LICENSE
ocrbridge_easyocr-3.1.1.dist-info/RECORD
