Metadata-Version: 2.4
Name: ocrbridge-easyocr
Version: 3.1.1
Summary: EasyOCR engine for OCR Bridge
License: MIT
License-File: LICENSE
Requires-Python: >=3.10
Requires-Dist: easyocr>=1.7.2
Requires-Dist: numpy>=1.24.0
Requires-Dist: ocrbridge-core>=3.1.0
Requires-Dist: pillow>=10.0.0
Requires-Dist: torch>=2.1.0
Provides-Extra: build
Requires-Dist: hatchling; extra == 'build'
Provides-Extra: test
Requires-Dist: pytest-mock>=3.12.0; extra == 'test'
Requires-Dist: pytest~=9.0; extra == 'test'
